{
  "lastScrapeTime": "2026-07-16T14:59:40.946Z",
  "lastGovScrapeTime": "2026-07-16T14:59:40.946Z",
  "results": [
    {
      "success": true,
      "source": "中国政府网-政策文件",
      "count": 1,
      "timestamp": "2026-07-16T14:34:01.207Z"
    },
    {
      "success": true,
      "source": "国家医保局-政策法规",
      "count": 14,
      "timestamp": "2026-07-16T14:34:07.556Z"
    },
    {
      "success": true,
      "source": "国家医保局-政策解读",
      "count": 14,
      "timestamp": "2026-07-16T14:34:13.229Z"
    },
    {
      "success": false,
      "source": "国家税务总局-政策法规",
      "count": 0,
      "timestamp": "2026-07-16T14:34:24.860Z"
    },
    {
      "success": false,
      "source": "国家税务总局-通知公告",
      "count": 0,
      "timestamp": "2026-07-16T14:34:36.147Z"
    },
    {
      "success": false,
      "source": "陕西省人社厅-首页",
      "count": 0,
      "timestamp": "2026-07-16T14:34:42.638Z"
    },
    {
      "success": false,
      "source": "住建部-首页",
      "count": 0,
      "timestamp": "2026-07-16T14:35:15.716Z"
    },
    {
      "success": false,
      "source": "人社部-政策文件",
      "count": 0,
      "timestamp": "2026-07-16T14:35:47.636Z"
    },
    {
      "success": true,
      "source": "中国政府网-最新政策",
      "count": 8,
      "timestamp": "2026-07-16T14:35:50.736Z"
    },
    {
      "success": true,
      "source": "中国政府网-政策解读",
      "count": 8,
      "timestamp": "2026-07-16T14:35:54.045Z"
    },
    {
      "success": false,
      "source": "国家税务总局-政策解读",
      "count": 0,
      "timestamp": "2026-07-16T14:36:05.633Z"
    },
    {
      "success": false,
      "source": "住建部-政策文件",
      "count": 0,
      "timestamp": "2026-07-16T14:37:44.814Z"
    },
    {
      "success": false,
      "source": "人社部-政策解读",
      "count": 0,
      "timestamp": "2026-07-16T14:38:18.196Z"
    },
    {
      "success": false,
      "source": "人社部-通知公告",
      "count": 0,
      "timestamp": "2026-07-16T14:38:55.553Z"
    },
    {
      "success": false,
      "source": "陕西省人社厅-政策文件",
      "count": 0,
      "timestamp": "2026-07-16T14:39:03.077Z"
    },
    {
      "success": false,
      "source": "陕西省人社厅-通知公告",
      "count": 0,
      "timestamp": "2026-07-16T14:39:14.365Z"
    },
    {
      "success": true,
      "source": "国家医保局-通知公告",
      "count": 3,
      "timestamp": "2026-07-16T14:39:22.424Z"
    },
    {
      "success": false,
      "source": "民政部-政策文件",
      "count": 0,
      "timestamp": "2026-07-16T14:41:01.621Z"
    },
    {
      "success": false,
      "source": "民政部-通知公告",
      "count": 0,
      "timestamp": "2026-07-16T14:42:40.786Z"
    },
    {
      "success": true,
      "source": "财政部-政策文件",
      "count": 19,
      "timestamp": "2026-07-16T14:42:42.774Z"
    },
    {
      "success": true,
      "source": "教育部-政策文件",
      "count": 1,
      "timestamp": "2026-07-16T14:42:50.389Z"
    },
    {
      "success": true,
      "source": "教育部-通知公告",
      "count": 1,
      "timestamp": "2026-07-16T14:42:54.320Z"
    },
    {
      "success": false,
      "source": "卫健委-政策文件",
      "count": 0,
      "timestamp": "2026-07-16T14:43:09.123Z"
    },
    {
      "success": true,
      "source": "中国政府网-国务院政策",
      "count": 8,
      "timestamp": "2026-07-16T14:43:13.642Z"
    },
    {
      "success": false,
      "source": "国家税务总局-税收政策",
      "count": 0,
      "timestamp": "2026-07-16T14:43:28.022Z"
    },
    {
      "success": false,
      "source": "住建部-政策法规",
      "count": 0,
      "timestamp": "2026-07-16T14:45:07.226Z"
    },
    {
      "success": false,
      "source": "民政部-养老服务",
      "count": 0,
      "timestamp": "2026-07-16T14:46:46.384Z"
    },
    {
      "success": true,
      "source": "财政部-政策解读",
      "count": 19,
      "timestamp": "2026-07-16T14:46:48.205Z"
    },
    {
      "success": false,
      "source": "社保局-社保政策",
      "count": 0,
      "timestamp": "2026-07-16T14:47:26.112Z"
    },
    {
      "success": true,
      "source": "教育部-政策解读",
      "count": 1,
      "timestamp": "2026-07-16T14:47:47.331Z"
    },
    {
      "success": false,
      "source": "卫健委-政策解读",
      "count": 0,
      "timestamp": "2026-07-16T14:48:04.664Z"
    },
    {
      "success": true,
      "source": "国家医保局-医保动态",
      "count": 14,
      "timestamp": "2026-07-16T14:48:12.982Z"
    },
    {
      "success": false,
      "source": "陕西省政府-政策文件",
      "count": 0,
      "timestamp": "2026-07-16T14:48:25.155Z"
    },
    {
      "success": false,
      "source": "人社部-养老保险",
      "count": 0,
      "timestamp": "2026-07-16T14:48:56.735Z"
    },
    {
      "success": false,
      "source": "人社部-社保保险",
      "count": 0,
      "timestamp": "2026-07-16T14:49:33.550Z"
    },
    {
      "success": true,
      "source": "教育部-新闻通气",
      "count": 1,
      "timestamp": "2026-07-16T14:49:43.036Z"
    },
    {
      "success": true,
      "source": "教育部-政策法规",
      "count": 1,
      "timestamp": "2026-07-16T14:49:56.399Z"
    },
    {
      "success": false,
      "source": "陕西省人社厅-社保服务",
      "count": 0,
      "timestamp": "2026-07-16T14:50:03.924Z"
    },
    {
      "success": false,
      "source": "陕西省人社厅-养老保险",
      "count": 0,
      "timestamp": "2026-07-16T14:50:11.448Z"
    },
    {
      "success": true,
      "source": "国家医保局-药品目录",
      "count": 14,
      "timestamp": "2026-07-16T14:50:20.563Z"
    },
    {
      "success": false,
      "source": "住建部-住房公积金",
      "count": 0,
      "timestamp": "2026-07-16T14:51:59.784Z"
    },
    {
      "success": true,
      "source": "中国政府网-国务院令",
      "count": 2,
      "timestamp": "2026-07-16T14:52:10.925Z"
    },
    {
      "success": false,
      "source": "国家税务总局-增值税",
      "count": 0,
      "timestamp": "2026-07-16T14:52:22.450Z"
    },
    {
      "success": true,
      "source": "国家税务总局-所得税",
      "count": 8,
      "timestamp": "2026-07-16T14:52:34.691Z"
    },
    {
      "success": true,
      "source": "财政部-综合政策",
      "count": 15,
      "timestamp": "2026-07-16T14:52:39.797Z"
    },
    {
      "success": false,
      "source": "民政部-社会救助",
      "count": 0,
      "timestamp": "2026-07-16T14:54:19.069Z"
    },
    {
      "success": false,
      "source": "民政部-社会福利",
      "count": 0,
      "timestamp": "2026-07-16T14:55:58.312Z"
    },
    {
      "success": false,
      "source": "住建部-住房保障",
      "count": 0,
      "timestamp": "2026-07-16T14:57:37.551Z"
    },
    {
      "success": false,
      "source": "陕西省人社厅-就业创业",
      "count": 0,
      "timestamp": "2026-07-16T14:57:45.077Z"
    },
    {
      "success": true,
      "source": "国家医保局-医保改革",
      "count": 12,
      "timestamp": "2026-07-16T14:57:52.149Z"
    },
    {
      "success": true,
      "source": "中国政府网-民生政策",
      "count": 8,
      "timestamp": "2026-07-16T14:58:01.524Z"
    },
    {
      "success": false,
      "source": "人社部-就业促进",
      "count": 0,
      "timestamp": "2026-07-16T14:58:35.001Z"
    },
    {
      "success": false,
      "source": "人社部-高校毕业生就业",
      "count": 0,
      "timestamp": "2026-07-16T14:59:07.218Z"
    },
    {
      "success": true,
      "source": "教育部-高校学生司",
      "count": 2,
      "timestamp": "2026-07-16T14:59:11.649Z"
    },
    {
      "success": true,
      "source": "教育部-职业教育",
      "count": 3,
      "timestamp": "2026-07-16T14:59:11.895Z"
    },
    {
      "success": true,
      "source": "中国政府网-就业政策",
      "count": 8,
      "timestamp": "2026-07-16T14:59:15.767Z"
    },
    {
      "success": false,
      "source": "人社部-人才流动",
      "count": 0,
      "timestamp": "2026-07-16T14:59:40.944Z"
    }
  ]
}