{
  "lastScrapeTime": "2026-07-16T04:12:33.134Z",
  "lastGovScrapeTime": "2026-07-16T04:12:33.134Z",
  "results": [
    {
      "success": true,
      "source": "中国政府网-政策文件",
      "count": 1,
      "timestamp": "2026-07-16T03:47:57.321Z"
    },
    {
      "success": true,
      "source": "国家医保局-政策法规",
      "count": 14,
      "timestamp": "2026-07-16T03:48:04.981Z"
    },
    {
      "success": true,
      "source": "国家医保局-政策解读",
      "count": 14,
      "timestamp": "2026-07-16T03:48:10.645Z"
    },
    {
      "success": false,
      "source": "国家税务总局-政策法规",
      "count": 0,
      "timestamp": "2026-07-16T03:48:22.474Z"
    },
    {
      "success": false,
      "source": "国家税务总局-通知公告",
      "count": 0,
      "timestamp": "2026-07-16T03:48:33.759Z"
    },
    {
      "success": false,
      "source": "陕西省人社厅-首页",
      "count": 0,
      "timestamp": "2026-07-16T03:48:37.849Z"
    },
    {
      "success": false,
      "source": "住建部-首页",
      "count": 0,
      "timestamp": "2026-07-16T03:49:10.903Z"
    },
    {
      "success": false,
      "source": "人社部-政策文件",
      "count": 0,
      "timestamp": "2026-07-16T03:49:41.452Z"
    },
    {
      "success": true,
      "source": "中国政府网-最新政策",
      "count": 8,
      "timestamp": "2026-07-16T03:49:44.842Z"
    },
    {
      "success": true,
      "source": "中国政府网-政策解读",
      "count": 8,
      "timestamp": "2026-07-16T03:49:47.546Z"
    },
    {
      "success": false,
      "source": "国家税务总局-政策解读",
      "count": 0,
      "timestamp": "2026-07-16T03:49:58.928Z"
    },
    {
      "success": false,
      "source": "住建部-政策文件",
      "count": 0,
      "timestamp": "2026-07-16T03:51:43.128Z"
    },
    {
      "success": false,
      "source": "人社部-政策解读",
      "count": 0,
      "timestamp": "2026-07-16T03:52:09.411Z"
    },
    {
      "success": false,
      "source": "人社部-通知公告",
      "count": 0,
      "timestamp": "2026-07-16T03:52:30.901Z"
    },
    {
      "success": false,
      "source": "陕西省人社厅-政策文件",
      "count": 0,
      "timestamp": "2026-07-16T03:52:38.425Z"
    },
    {
      "success": false,
      "source": "陕西省人社厅-通知公告",
      "count": 0,
      "timestamp": "2026-07-16T03:52:49.712Z"
    },
    {
      "success": true,
      "source": "国家医保局-通知公告",
      "count": 3,
      "timestamp": "2026-07-16T03:52:56.745Z"
    },
    {
      "success": false,
      "source": "民政部-政策文件",
      "count": 0,
      "timestamp": "2026-07-16T03:54:35.933Z"
    },
    {
      "success": false,
      "source": "民政部-通知公告",
      "count": 0,
      "timestamp": "2026-07-16T03:56:14.415Z"
    },
    {
      "success": true,
      "source": "财政部-政策文件",
      "count": 19,
      "timestamp": "2026-07-16T03:56:18.775Z"
    },
    {
      "success": true,
      "source": "教育部-政策文件",
      "count": 1,
      "timestamp": "2026-07-16T03:56:29.981Z"
    },
    {
      "success": true,
      "source": "教育部-通知公告",
      "count": 1,
      "timestamp": "2026-07-16T03:56:34.273Z"
    },
    {
      "success": false,
      "source": "卫健委-政策文件",
      "count": 0,
      "timestamp": "2026-07-16T03:56:42.679Z"
    },
    {
      "success": true,
      "source": "中国政府网-国务院政策",
      "count": 8,
      "timestamp": "2026-07-16T03:56:46.002Z"
    },
    {
      "success": false,
      "source": "国家税务总局-税收政策",
      "count": 0,
      "timestamp": "2026-07-16T03:56:57.591Z"
    },
    {
      "success": false,
      "source": "住建部-政策法规",
      "count": 0,
      "timestamp": "2026-07-16T03:58:36.761Z"
    },
    {
      "success": false,
      "source": "民政部-养老服务",
      "count": 0,
      "timestamp": "2026-07-16T04:00:15.917Z"
    },
    {
      "success": true,
      "source": "财政部-政策解读",
      "count": 19,
      "timestamp": "2026-07-16T04:00:18.714Z"
    },
    {
      "success": false,
      "source": "社保局-社保政策",
      "count": 0,
      "timestamp": "2026-07-16T04:00:43.652Z"
    },
    {
      "success": true,
      "source": "教育部-政策解读",
      "count": 1,
      "timestamp": "2026-07-16T04:00:55.460Z"
    },
    {
      "success": false,
      "source": "卫健委-政策解读",
      "count": 0,
      "timestamp": "2026-07-16T04:01:03.230Z"
    },
    {
      "success": true,
      "source": "国家医保局-医保动态",
      "count": 14,
      "timestamp": "2026-07-16T04:01:09.484Z"
    },
    {
      "success": false,
      "source": "陕西省政府-政策文件",
      "count": 0,
      "timestamp": "2026-07-16T04:01:21.140Z"
    },
    {
      "success": false,
      "source": "人社部-养老保险",
      "count": 0,
      "timestamp": "2026-07-16T04:01:51.531Z"
    },
    {
      "success": false,
      "source": "人社部-社保保险",
      "count": 0,
      "timestamp": "2026-07-16T04:02:20.140Z"
    },
    {
      "success": true,
      "source": "教育部-新闻通气",
      "count": 1,
      "timestamp": "2026-07-16T04:02:47.393Z"
    },
    {
      "success": true,
      "source": "教育部-政策法规",
      "count": 1,
      "timestamp": "2026-07-16T04:02:54.874Z"
    },
    {
      "success": false,
      "source": "陕西省人社厅-社保服务",
      "count": 0,
      "timestamp": "2026-07-16T04:03:02.395Z"
    },
    {
      "success": false,
      "source": "陕西省人社厅-养老保险",
      "count": 0,
      "timestamp": "2026-07-16T04:03:09.918Z"
    },
    {
      "success": true,
      "source": "国家医保局-药品目录",
      "count": 14,
      "timestamp": "2026-07-16T04:03:16.736Z"
    },
    {
      "success": false,
      "source": "住建部-住房公积金",
      "count": 0,
      "timestamp": "2026-07-16T04:04:55.896Z"
    },
    {
      "success": true,
      "source": "中国政府网-国务院令",
      "count": 3,
      "timestamp": "2026-07-16T04:05:08.432Z"
    },
    {
      "success": false,
      "source": "国家税务总局-增值税",
      "count": 0,
      "timestamp": "2026-07-16T04:05:20.086Z"
    },
    {
      "success": false,
      "source": "国家税务总局-所得税",
      "count": 0,
      "timestamp": "2026-07-16T04:05:31.373Z"
    },
    {
      "success": true,
      "source": "财政部-综合政策",
      "count": 15,
      "timestamp": "2026-07-16T04:05:41.979Z"
    },
    {
      "success": false,
      "source": "民政部-社会救助",
      "count": 0,
      "timestamp": "2026-07-16T04:07:21.138Z"
    },
    {
      "success": false,
      "source": "民政部-社会福利",
      "count": 0,
      "timestamp": "2026-07-16T04:09:00.292Z"
    },
    {
      "success": false,
      "source": "住建部-住房保障",
      "count": 0,
      "timestamp": "2026-07-16T04:10:39.461Z"
    },
    {
      "success": false,
      "source": "陕西省人社厅-就业创业",
      "count": 0,
      "timestamp": "2026-07-16T04:10:46.986Z"
    },
    {
      "success": true,
      "source": "国家医保局-医保改革",
      "count": 12,
      "timestamp": "2026-07-16T04:10:55.571Z"
    },
    {
      "success": true,
      "source": "中国政府网-民生政策",
      "count": 8,
      "timestamp": "2026-07-16T04:11:03.877Z"
    },
    {
      "success": false,
      "source": "人社部-就业促进",
      "count": 0,
      "timestamp": "2026-07-16T04:11:33.110Z"
    },
    {
      "success": false,
      "source": "人社部-高校毕业生就业",
      "count": 0,
      "timestamp": "2026-07-16T04:11:58.325Z"
    },
    {
      "success": true,
      "source": "教育部-高校学生司",
      "count": 2,
      "timestamp": "2026-07-16T04:12:03.977Z"
    },
    {
      "success": true,
      "source": "教育部-职业教育",
      "count": 3,
      "timestamp": "2026-07-16T04:12:04.379Z"
    },
    {
      "success": true,
      "source": "中国政府网-就业政策",
      "count": 8,
      "timestamp": "2026-07-16T04:12:08.902Z"
    },
    {
      "success": false,
      "source": "人社部-人才流动",
      "count": 0,
      "timestamp": "2026-07-16T04:12:33.132Z"
    }
  ]
}