{
  "lastScrapeTime": "2026-07-01T20:48:38.808Z",
  "lastGovScrapeTime": "2026-07-01T20:48:38.808Z",
  "results": [
    {
      "success": true,
      "source": "中国政府网-政策文件",
      "count": 1,
      "timestamp": "2026-07-01T20:24:35.838Z"
    },
    {
      "success": true,
      "source": "国家医保局-政策法规",
      "count": 14,
      "timestamp": "2026-07-01T20:24:42.607Z"
    },
    {
      "success": true,
      "source": "国家医保局-政策解读",
      "count": 14,
      "timestamp": "2026-07-01T20:24:47.917Z"
    },
    {
      "success": true,
      "source": "国家税务总局-政策法规",
      "count": 12,
      "timestamp": "2026-07-01T20:24:52.517Z"
    },
    {
      "success": true,
      "source": "国家税务总局-通知公告",
      "count": 11,
      "timestamp": "2026-07-01T20:25:14.268Z"
    },
    {
      "success": false,
      "source": "陕西省人社厅-首页",
      "count": 0,
      "timestamp": "2026-07-01T20:25:18.615Z"
    },
    {
      "success": false,
      "source": "住建部-首页",
      "count": 0,
      "timestamp": "2026-07-01T20:25:51.663Z"
    },
    {
      "success": false,
      "source": "人社部-政策文件",
      "count": 0,
      "timestamp": "2026-07-01T20:26:14.072Z"
    },
    {
      "success": true,
      "source": "中国政府网-最新政策",
      "count": 7,
      "timestamp": "2026-07-01T20:26:17.742Z"
    },
    {
      "success": true,
      "source": "中国政府网-政策解读",
      "count": 7,
      "timestamp": "2026-07-01T20:26:20.377Z"
    },
    {
      "success": false,
      "source": "国家税务总局-政策解读",
      "count": 0,
      "timestamp": "2026-07-01T20:26:39.752Z"
    },
    {
      "success": false,
      "source": "住建部-政策文件",
      "count": 0,
      "timestamp": "2026-07-01T20:28:18.911Z"
    },
    {
      "success": false,
      "source": "人社部-政策解读",
      "count": 0,
      "timestamp": "2026-07-01T20:28:45.885Z"
    },
    {
      "success": false,
      "source": "人社部-通知公告",
      "count": 0,
      "timestamp": "2026-07-01T20:29:14.876Z"
    },
    {
      "success": false,
      "source": "陕西省人社厅-政策文件",
      "count": 0,
      "timestamp": "2026-07-01T20:29:22.400Z"
    },
    {
      "success": false,
      "source": "陕西省人社厅-通知公告",
      "count": 0,
      "timestamp": "2026-07-01T20:29:33.688Z"
    },
    {
      "success": true,
      "source": "国家医保局-通知公告",
      "count": 2,
      "timestamp": "2026-07-01T20:29:39.960Z"
    },
    {
      "success": false,
      "source": "民政部-政策文件",
      "count": 0,
      "timestamp": "2026-07-01T20:31:19.108Z"
    },
    {
      "success": false,
      "source": "民政部-通知公告",
      "count": 0,
      "timestamp": "2026-07-01T20:32:54.843Z"
    },
    {
      "success": true,
      "source": "财政部-政策文件",
      "count": 19,
      "timestamp": "2026-07-01T20:32:57.767Z"
    },
    {
      "success": true,
      "source": "教育部-政策文件",
      "count": 1,
      "timestamp": "2026-07-01T20:33:11.353Z"
    },
    {
      "success": true,
      "source": "教育部-通知公告",
      "count": 1,
      "timestamp": "2026-07-01T20:33:14.967Z"
    },
    {
      "success": false,
      "source": "卫健委-政策文件",
      "count": 0,
      "timestamp": "2026-07-01T20:33:22.351Z"
    },
    {
      "success": true,
      "source": "中国政府网-国务院政策",
      "count": 7,
      "timestamp": "2026-07-01T20:33:26.031Z"
    },
    {
      "success": true,
      "source": "国家税务总局-税收政策",
      "count": 11,
      "timestamp": "2026-07-01T20:33:54.860Z"
    },
    {
      "success": false,
      "source": "住建部-政策法规",
      "count": 0,
      "timestamp": "2026-07-01T20:35:34.037Z"
    },
    {
      "success": false,
      "source": "民政部-养老服务",
      "count": 0,
      "timestamp": "2026-07-01T20:37:13.189Z"
    },
    {
      "success": true,
      "source": "财政部-政策解读",
      "count": 17,
      "timestamp": "2026-07-01T20:37:15.743Z"
    },
    {
      "success": false,
      "source": "社保局-社保政策",
      "count": 0,
      "timestamp": "2026-07-01T20:37:41.154Z"
    },
    {
      "success": true,
      "source": "教育部-政策解读",
      "count": 1,
      "timestamp": "2026-07-01T20:37:51.458Z"
    },
    {
      "success": false,
      "source": "卫健委-政策解读",
      "count": 0,
      "timestamp": "2026-07-01T20:37:58.415Z"
    },
    {
      "success": true,
      "source": "国家医保局-医保动态",
      "count": 14,
      "timestamp": "2026-07-01T20:38:04.565Z"
    },
    {
      "success": false,
      "source": "陕西省政府-政策文件",
      "count": 0,
      "timestamp": "2026-07-01T20:38:16.226Z"
    },
    {
      "success": false,
      "source": "人社部-养老保险",
      "count": 0,
      "timestamp": "2026-07-01T20:38:40.302Z"
    },
    {
      "success": false,
      "source": "人社部-社保保险",
      "count": 0,
      "timestamp": "2026-07-01T20:39:02.383Z"
    },
    {
      "success": true,
      "source": "教育部-新闻通气",
      "count": 1,
      "timestamp": "2026-07-01T20:39:08.880Z"
    },
    {
      "success": true,
      "source": "教育部-政策法规",
      "count": 1,
      "timestamp": "2026-07-01T20:39:10.842Z"
    },
    {
      "success": false,
      "source": "陕西省人社厅-社保服务",
      "count": 0,
      "timestamp": "2026-07-01T20:39:18.364Z"
    },
    {
      "success": false,
      "source": "陕西省人社厅-养老保险",
      "count": 0,
      "timestamp": "2026-07-01T20:39:25.886Z"
    },
    {
      "success": true,
      "source": "国家医保局-药品目录",
      "count": 14,
      "timestamp": "2026-07-01T20:39:32.063Z"
    },
    {
      "success": false,
      "source": "住建部-住房公积金",
      "count": 0,
      "timestamp": "2026-07-01T20:41:11.244Z"
    },
    {
      "success": true,
      "source": "中国政府网-国务院令",
      "count": 4,
      "timestamp": "2026-07-01T20:41:18.417Z"
    },
    {
      "success": false,
      "source": "国家税务总局-增值税",
      "count": 0,
      "timestamp": "2026-07-01T20:41:33.604Z"
    },
    {
      "success": true,
      "source": "国家税务总局-所得税",
      "count": 6,
      "timestamp": "2026-07-01T20:41:43.284Z"
    },
    {
      "success": true,
      "source": "财政部-综合政策",
      "count": 14,
      "timestamp": "2026-07-01T20:41:52.629Z"
    },
    {
      "success": false,
      "source": "民政部-社会救助",
      "count": 0,
      "timestamp": "2026-07-01T20:43:31.789Z"
    },
    {
      "success": false,
      "source": "民政部-社会福利",
      "count": 0,
      "timestamp": "2026-07-01T20:45:10.636Z"
    },
    {
      "success": false,
      "source": "住建部-住房保障",
      "count": 0,
      "timestamp": "2026-07-01T20:46:49.815Z"
    },
    {
      "success": false,
      "source": "陕西省人社厅-就业创业",
      "count": 0,
      "timestamp": "2026-07-01T20:46:57.339Z"
    },
    {
      "success": true,
      "source": "国家医保局-医保改革",
      "count": 13,
      "timestamp": "2026-07-01T20:47:03.359Z"
    },
    {
      "success": true,
      "source": "中国政府网-民生政策",
      "count": 7,
      "timestamp": "2026-07-01T20:47:07.972Z"
    },
    {
      "success": false,
      "source": "人社部-就业促进",
      "count": 0,
      "timestamp": "2026-07-01T20:47:31.869Z"
    },
    {
      "success": false,
      "source": "人社部-高校毕业生就业",
      "count": 0,
      "timestamp": "2026-07-01T20:47:55.567Z"
    },
    {
      "success": true,
      "source": "教育部-高校学生司",
      "count": 3,
      "timestamp": "2026-07-01T20:48:00.022Z"
    },
    {
      "success": true,
      "source": "教育部-职业教育",
      "count": 3,
      "timestamp": "2026-07-01T20:48:00.337Z"
    },
    {
      "success": true,
      "source": "中国政府网-就业政策",
      "count": 7,
      "timestamp": "2026-07-01T20:48:17.595Z"
    },
    {
      "success": false,
      "source": "人社部-人才流动",
      "count": 0,
      "timestamp": "2026-07-01T20:48:38.806Z"
    }
  ]
}