{
  "lastScrapeTime": "2026-07-23T09:37:30.058Z",
  "lastGovScrapeTime": "2026-07-23T09:37:30.058Z",
  "results": [
    {
      "success": true,
      "source": "中国政府网-政策文件",
      "count": 4,
      "timestamp": "2026-07-23T09:09:58.572Z"
    },
    {
      "success": true,
      "source": "国家医保局-政策法规",
      "count": 14,
      "timestamp": "2026-07-23T09:10:08.295Z"
    },
    {
      "success": true,
      "source": "国家医保局-政策解读",
      "count": 14,
      "timestamp": "2026-07-23T09:10:14.647Z"
    },
    {
      "success": false,
      "source": "国家税务总局-政策法规",
      "count": 0,
      "timestamp": "2026-07-23T09:10:26.054Z"
    },
    {
      "success": false,
      "source": "国家税务总局-通知公告",
      "count": 0,
      "timestamp": "2026-07-23T09:10:37.335Z"
    },
    {
      "success": false,
      "source": "陕西省人社厅-首页",
      "count": 0,
      "timestamp": "2026-07-23T09:10:46.789Z"
    },
    {
      "success": false,
      "source": "住建部-首页",
      "count": 0,
      "timestamp": "2026-07-23T09:11:19.859Z"
    },
    {
      "success": false,
      "source": "人社部-政策文件",
      "count": 0,
      "timestamp": "2026-07-23T09:11:53.859Z"
    },
    {
      "success": true,
      "source": "中国政府网-最新政策",
      "count": 8,
      "timestamp": "2026-07-23T09:11:56.833Z"
    },
    {
      "success": true,
      "source": "中国政府网-政策解读",
      "count": 8,
      "timestamp": "2026-07-23T09:11:59.983Z"
    },
    {
      "success": false,
      "source": "国家税务总局-政策解读",
      "count": 0,
      "timestamp": "2026-07-23T09:12:11.513Z"
    },
    {
      "success": false,
      "source": "住建部-政策文件",
      "count": 0,
      "timestamp": "2026-07-23T09:13:50.688Z"
    },
    {
      "success": false,
      "source": "人社部-政策解读",
      "count": 0,
      "timestamp": "2026-07-23T09:14:18.884Z"
    },
    {
      "success": false,
      "source": "人社部-通知公告",
      "count": 0,
      "timestamp": "2026-07-23T09:14:48.517Z"
    },
    {
      "success": false,
      "source": "陕西省人社厅-政策文件",
      "count": 0,
      "timestamp": "2026-07-23T09:14:56.038Z"
    },
    {
      "success": false,
      "source": "陕西省人社厅-通知公告",
      "count": 0,
      "timestamp": "2026-07-23T09:15:07.320Z"
    },
    {
      "success": true,
      "source": "国家医保局-通知公告",
      "count": 1,
      "timestamp": "2026-07-23T09:17:25.514Z"
    },
    {
      "success": false,
      "source": "民政部-政策文件",
      "count": 0,
      "timestamp": "2026-07-23T09:19:04.662Z"
    },
    {
      "success": false,
      "source": "民政部-通知公告",
      "count": 0,
      "timestamp": "2026-07-23T09:20:40.528Z"
    },
    {
      "success": true,
      "source": "财政部-政策文件",
      "count": 19,
      "timestamp": "2026-07-23T09:20:43.069Z"
    },
    {
      "success": true,
      "source": "教育部-政策文件",
      "count": 1,
      "timestamp": "2026-07-23T09:20:58.391Z"
    },
    {
      "success": true,
      "source": "教育部-通知公告",
      "count": 1,
      "timestamp": "2026-07-23T09:21:02.361Z"
    },
    {
      "success": false,
      "source": "卫健委-政策文件",
      "count": 0,
      "timestamp": "2026-07-23T09:21:10.940Z"
    },
    {
      "success": true,
      "source": "中国政府网-国务院政策",
      "count": 8,
      "timestamp": "2026-07-23T09:21:14.656Z"
    },
    {
      "success": false,
      "source": "国家税务总局-税收政策",
      "count": 0,
      "timestamp": "2026-07-23T09:21:26.661Z"
    },
    {
      "success": false,
      "source": "住建部-政策法规",
      "count": 0,
      "timestamp": "2026-07-23T09:23:05.825Z"
    },
    {
      "success": false,
      "source": "民政部-养老服务",
      "count": 0,
      "timestamp": "2026-07-23T09:24:45.008Z"
    },
    {
      "success": true,
      "source": "财政部-政策解读",
      "count": 18,
      "timestamp": "2026-07-23T09:24:46.941Z"
    },
    {
      "success": false,
      "source": "社保局-社保政策",
      "count": 0,
      "timestamp": "2026-07-23T09:25:14.650Z"
    },
    {
      "success": true,
      "source": "教育部-政策解读",
      "count": 1,
      "timestamp": "2026-07-23T09:25:34.577Z"
    },
    {
      "success": false,
      "source": "卫健委-政策解读",
      "count": 0,
      "timestamp": "2026-07-23T09:25:44.169Z"
    },
    {
      "success": true,
      "source": "国家医保局-医保动态",
      "count": 14,
      "timestamp": "2026-07-23T09:25:50.726Z"
    },
    {
      "success": false,
      "source": "陕西省政府-政策文件",
      "count": 0,
      "timestamp": "2026-07-23T09:26:02.637Z"
    },
    {
      "success": false,
      "source": "人社部-养老保险",
      "count": 0,
      "timestamp": "2026-07-23T09:26:32.326Z"
    },
    {
      "success": false,
      "source": "人社部-社保保险",
      "count": 0,
      "timestamp": "2026-07-23T09:27:00.832Z"
    },
    {
      "success": true,
      "source": "教育部-新闻通气",
      "count": 1,
      "timestamp": "2026-07-23T09:27:11.775Z"
    },
    {
      "success": true,
      "source": "教育部-政策法规",
      "count": 1,
      "timestamp": "2026-07-23T09:27:19.146Z"
    },
    {
      "success": false,
      "source": "陕西省人社厅-社保服务",
      "count": 0,
      "timestamp": "2026-07-23T09:27:26.670Z"
    },
    {
      "success": false,
      "source": "陕西省人社厅-养老保险",
      "count": 0,
      "timestamp": "2026-07-23T09:27:34.194Z"
    },
    {
      "success": true,
      "source": "国家医保局-药品目录",
      "count": 14,
      "timestamp": "2026-07-23T09:28:00.143Z"
    },
    {
      "success": false,
      "source": "住建部-住房公积金",
      "count": 0,
      "timestamp": "2026-07-23T09:29:39.336Z"
    },
    {
      "success": true,
      "source": "中国政府网-国务院令",
      "count": 6,
      "timestamp": "2026-07-23T09:29:45.506Z"
    },
    {
      "success": false,
      "source": "国家税务总局-增值税",
      "count": 0,
      "timestamp": "2026-07-23T09:29:57.095Z"
    },
    {
      "success": false,
      "source": "国家税务总局-所得税",
      "count": 0,
      "timestamp": "2026-07-23T09:30:08.383Z"
    },
    {
      "success": true,
      "source": "财政部-综合政策",
      "count": 14,
      "timestamp": "2026-07-23T09:30:17.403Z"
    },
    {
      "success": false,
      "source": "民政部-社会救助",
      "count": 0,
      "timestamp": "2026-07-23T09:31:56.551Z"
    },
    {
      "success": false,
      "source": "民政部-社会福利",
      "count": 0,
      "timestamp": "2026-07-23T09:33:35.702Z"
    },
    {
      "success": false,
      "source": "住建部-住房保障",
      "count": 0,
      "timestamp": "2026-07-23T09:35:14.874Z"
    },
    {
      "success": false,
      "source": "陕西省人社厅-就业创业",
      "count": 0,
      "timestamp": "2026-07-23T09:35:22.400Z"
    },
    {
      "success": true,
      "source": "国家医保局-医保改革",
      "count": 12,
      "timestamp": "2026-07-23T09:35:31.269Z"
    },
    {
      "success": true,
      "source": "中国政府网-民生政策",
      "count": 8,
      "timestamp": "2026-07-23T09:35:44.314Z"
    },
    {
      "success": false,
      "source": "人社部-就业促进",
      "count": 0,
      "timestamp": "2026-07-23T09:36:14.317Z"
    },
    {
      "success": false,
      "source": "人社部-高校毕业生就业",
      "count": 0,
      "timestamp": "2026-07-23T09:36:44.555Z"
    },
    {
      "success": true,
      "source": "教育部-高校学生司",
      "count": 2,
      "timestamp": "2026-07-23T09:37:04.767Z"
    },
    {
      "success": true,
      "source": "教育部-职业教育",
      "count": 3,
      "timestamp": "2026-07-23T09:37:05.027Z"
    },
    {
      "success": true,
      "source": "中国政府网-就业政策",
      "count": 8,
      "timestamp": "2026-07-23T09:37:08.529Z"
    },
    {
      "success": false,
      "source": "人社部-人才流动",
      "count": 0,
      "timestamp": "2026-07-23T09:37:30.055Z"
    }
  ]
}