{
  "lastScrapeTime": "2026-07-16T06:39:55.504Z",
  "lastGovScrapeTime": "2026-07-16T06:39:55.504Z",
  "results": [
    {
      "success": true,
      "source": "中国政府网-政策文件",
      "count": 1,
      "timestamp": "2026-07-16T06:15:34.154Z"
    },
    {
      "success": true,
      "source": "国家医保局-政策法规",
      "count": 14,
      "timestamp": "2026-07-16T06:15:41.040Z"
    },
    {
      "success": true,
      "source": "国家医保局-政策解读",
      "count": 14,
      "timestamp": "2026-07-16T06:15:48.094Z"
    },
    {
      "success": true,
      "source": "国家税务总局-政策法规",
      "count": 12,
      "timestamp": "2026-07-16T06:15:49.837Z"
    },
    {
      "success": false,
      "source": "国家税务总局-通知公告",
      "count": 0,
      "timestamp": "2026-07-16T06:16:08.356Z"
    },
    {
      "success": false,
      "source": "陕西省人社厅-首页",
      "count": 0,
      "timestamp": "2026-07-16T06:16:17.329Z"
    },
    {
      "success": false,
      "source": "住建部-首页",
      "count": 0,
      "timestamp": "2026-07-16T06:16:50.389Z"
    },
    {
      "success": false,
      "source": "人社部-政策文件",
      "count": 0,
      "timestamp": "2026-07-16T06:17:17.400Z"
    },
    {
      "success": true,
      "source": "中国政府网-最新政策",
      "count": 8,
      "timestamp": "2026-07-16T06:17:21.796Z"
    },
    {
      "success": true,
      "source": "中国政府网-政策解读",
      "count": 8,
      "timestamp": "2026-07-16T06:17:25.877Z"
    },
    {
      "success": false,
      "source": "国家税务总局-政策解读",
      "count": 0,
      "timestamp": "2026-07-16T06:17:40.907Z"
    },
    {
      "success": false,
      "source": "住建部-政策文件",
      "count": 0,
      "timestamp": "2026-07-16T06:19:20.171Z"
    },
    {
      "success": false,
      "source": "人社部-政策解读",
      "count": 0,
      "timestamp": "2026-07-16T06:19:45.790Z"
    },
    {
      "success": false,
      "source": "人社部-通知公告",
      "count": 0,
      "timestamp": "2026-07-16T06:20:10.151Z"
    },
    {
      "success": false,
      "source": "陕西省人社厅-政策文件",
      "count": 0,
      "timestamp": "2026-07-16T06:20:17.675Z"
    },
    {
      "success": false,
      "source": "陕西省人社厅-通知公告",
      "count": 0,
      "timestamp": "2026-07-16T06:20:28.961Z"
    },
    {
      "success": true,
      "source": "国家医保局-通知公告",
      "count": 3,
      "timestamp": "2026-07-16T06:20:34.831Z"
    },
    {
      "success": false,
      "source": "民政部-政策文件",
      "count": 0,
      "timestamp": "2026-07-16T06:22:13.980Z"
    },
    {
      "success": false,
      "source": "民政部-通知公告",
      "count": 0,
      "timestamp": "2026-07-16T06:23:50.749Z"
    },
    {
      "success": true,
      "source": "财政部-政策文件",
      "count": 19,
      "timestamp": "2026-07-16T06:23:52.416Z"
    },
    {
      "success": true,
      "source": "教育部-政策文件",
      "count": 1,
      "timestamp": "2026-07-16T06:24:03.480Z"
    },
    {
      "success": true,
      "source": "教育部-通知公告",
      "count": 1,
      "timestamp": "2026-07-16T06:24:06.929Z"
    },
    {
      "success": false,
      "source": "卫健委-政策文件",
      "count": 0,
      "timestamp": "2026-07-16T06:24:14.655Z"
    },
    {
      "success": true,
      "source": "中国政府网-国务院政策",
      "count": 8,
      "timestamp": "2026-07-16T06:24:19.744Z"
    },
    {
      "success": false,
      "source": "国家税务总局-税收政策",
      "count": 0,
      "timestamp": "2026-07-16T06:24:34.913Z"
    },
    {
      "success": false,
      "source": "住建部-政策法规",
      "count": 0,
      "timestamp": "2026-07-16T06:26:14.101Z"
    },
    {
      "success": false,
      "source": "民政部-养老服务",
      "count": 0,
      "timestamp": "2026-07-16T06:27:53.262Z"
    },
    {
      "success": true,
      "source": "财政部-政策解读",
      "count": 19,
      "timestamp": "2026-07-16T06:27:54.663Z"
    },
    {
      "success": false,
      "source": "社保局-社保政策",
      "count": 0,
      "timestamp": "2026-07-16T06:28:23.681Z"
    },
    {
      "success": true,
      "source": "教育部-政策解读",
      "count": 1,
      "timestamp": "2026-07-16T06:28:39.343Z"
    },
    {
      "success": false,
      "source": "卫健委-政策解读",
      "count": 0,
      "timestamp": "2026-07-16T06:28:47.007Z"
    },
    {
      "success": true,
      "source": "国家医保局-医保动态",
      "count": 14,
      "timestamp": "2026-07-16T06:28:53.362Z"
    },
    {
      "success": false,
      "source": "陕西省政府-政策文件",
      "count": 0,
      "timestamp": "2026-07-16T06:29:05.056Z"
    },
    {
      "success": false,
      "source": "人社部-养老保险",
      "count": 0,
      "timestamp": "2026-07-16T06:29:30.527Z"
    },
    {
      "success": false,
      "source": "人社部-社保保险",
      "count": 0,
      "timestamp": "2026-07-16T06:29:55.507Z"
    },
    {
      "success": true,
      "source": "教育部-新闻通气",
      "count": 1,
      "timestamp": "2026-07-16T06:30:16.887Z"
    },
    {
      "success": true,
      "source": "教育部-政策法规",
      "count": 1,
      "timestamp": "2026-07-16T06:30:24.994Z"
    },
    {
      "success": false,
      "source": "陕西省人社厅-社保服务",
      "count": 0,
      "timestamp": "2026-07-16T06:30:32.520Z"
    },
    {
      "success": false,
      "source": "陕西省人社厅-养老保险",
      "count": 0,
      "timestamp": "2026-07-16T06:30:40.044Z"
    },
    {
      "success": true,
      "source": "国家医保局-药品目录",
      "count": 14,
      "timestamp": "2026-07-16T06:30:46.199Z"
    },
    {
      "success": false,
      "source": "住建部-住房公积金",
      "count": 0,
      "timestamp": "2026-07-16T06:32:25.359Z"
    },
    {
      "success": true,
      "source": "中国政府网-国务院令",
      "count": 3,
      "timestamp": "2026-07-16T06:32:33.852Z"
    },
    {
      "success": false,
      "source": "国家税务总局-增值税",
      "count": 0,
      "timestamp": "2026-07-16T06:32:50.301Z"
    },
    {
      "success": false,
      "source": "国家税务总局-所得税",
      "count": 0,
      "timestamp": "2026-07-16T06:33:09.176Z"
    },
    {
      "success": true,
      "source": "财政部-综合政策",
      "count": 15,
      "timestamp": "2026-07-16T06:33:13.462Z"
    },
    {
      "success": false,
      "source": "民政部-社会救助",
      "count": 0,
      "timestamp": "2026-07-16T06:34:51.006Z"
    },
    {
      "success": false,
      "source": "民政部-社会福利",
      "count": 0,
      "timestamp": "2026-07-16T06:36:30.206Z"
    },
    {
      "success": false,
      "source": "住建部-住房保障",
      "count": 0,
      "timestamp": "2026-07-16T06:38:09.368Z"
    },
    {
      "success": false,
      "source": "陕西省人社厅-就业创业",
      "count": 0,
      "timestamp": "2026-07-16T06:38:16.891Z"
    },
    {
      "success": true,
      "source": "国家医保局-医保改革",
      "count": 12,
      "timestamp": "2026-07-16T06:38:24.678Z"
    },
    {
      "success": true,
      "source": "中国政府网-民生政策",
      "count": 8,
      "timestamp": "2026-07-16T06:38:28.831Z"
    },
    {
      "success": false,
      "source": "人社部-就业促进",
      "count": 0,
      "timestamp": "2026-07-16T06:38:49.388Z"
    },
    {
      "success": false,
      "source": "人社部-高校毕业生就业",
      "count": 0,
      "timestamp": "2026-07-16T06:39:14.334Z"
    },
    {
      "success": true,
      "source": "教育部-高校学生司",
      "count": 2,
      "timestamp": "2026-07-16T06:39:23.568Z"
    },
    {
      "success": true,
      "source": "教育部-职业教育",
      "count": 3,
      "timestamp": "2026-07-16T06:39:23.800Z"
    },
    {
      "success": true,
      "source": "中国政府网-就业政策",
      "count": 8,
      "timestamp": "2026-07-16T06:39:28.265Z"
    },
    {
      "success": false,
      "source": "人社部-人才流动",
      "count": 0,
      "timestamp": "2026-07-16T06:39:55.503Z"
    }
  ]
}